co/lab3/lab3-2/MEMORY.v
`timescale 1ns/1ps

module MEMORY(
	clk,
	rst,
	ALUout,
	XM_RD,
    XM_RegWrite,

	MW_ALUout,
	MW_RD,
    MW_RegWrite
);
input clk, rst;
input [31:0] ALUout;
input [4:0] XM_RD;
input XM_RegWrite;

output reg [31:0] MW_ALUout;
output reg [4:0] MW_RD;
output reg MW_RegWrite;

//data memory
reg [31:0] DM [0:127];
/*
//always store word to data memory
always @(posedge clk)
  if(XM_MemWrite)
    DM[ALUout[6:0]] <= XM_MD;
*/

//send to Dst REG: "load word from data memory" or  "ALUout"
always @(posedge clk) begin
    if(rst) begin
        MW_ALUout	<=	32'b0;
        MW_RD		<=	5'b0;
        MW_RegWrite <= 0;
    end
    else begin
        MW_ALUout	<=	ALUout;
        MW_RD		<=	XM_RD;
        MW_RegWrite <= XM_RegWrite;
    end
end

endmodule

co/lab3/lab3-2/EXECUTION.v
`timescale 1ns/1ps

module EXECUTION(
    clk,
    rst,
    A,
    B,
    DX_RD,
    ALUctr,
    DX_Branch,
    DX_RegWrite,

    ALUout,
    XM_RD,
    XF_Branch,
    XM_RegWrite
);

input clk,rst,ALUop;
input [31:0] A,B;
input [4:0]DX_RD;
input [2:0] ALUctr;
input DX_Branch;
input DX_RegWrite;

output reg [31:0]ALUout;
output reg [4:0]XM_RD;
output reg XF_Branch;
output reg XM_RegWrite;

//set pipeline register
always @(posedge clk or posedge rst) begin
    if(rst) begin
        XM_RD	<= 5'd0;
        XF_Branch <= 0;
        XM_RegWrite <= 0;
    end 
    else begin
        XM_RD <= DX_RD;
        XF_Branch <= DX_Branch;
        XM_RegWrite <= DX_RegWrite;
    end
end

// calculating ALUout
always @(posedge clk or posedge rst) begin
    if(rst) begin
        ALUout	<= 32'd0;
    end 
    else begin
        case(ALUctr)
            3'b010: //add //lw //sw
            begin
                ALUout <= A+B;
            end
            3'b110: //sub
            begin
                ALUout <= A - B;
            end
            3'b000: // and
            begin
                ALUout <= A & B;
            end
            3'b001: // or
            begin
                ALUout <= A | B;
            end
            3'b111: // slt
            begin
                ALUout <= (A < B)? 1: 0;
            end
        endcase
    end
end
endmodule

co/lab3/lab3-2/INSTRUCTION_DECODE.v
`timescale 1ns/1ps

module INSTRUCTION_DECODE(
	clk,
	rst,
	IR,
	PC,
	MW_RD,
	MW_ALUout,
    MW_RegWrite,

	A,
	B,
	RD,
	ALUctr,
    Jump,
    JAddr,
    Branch,
    DX_RegWrite
);

input clk,rst;
input [31:0]IR, PC, MW_ALUout;
input [4:0] MW_RD;
input MW_RegWrite;

output reg [31:0] A, B;
output reg [4:0] RD;
output reg [2:0] ALUctr;
output reg Jump;
output reg [31:0] JAddr;
output reg Branch;
output reg DX_RegWrite;

//register file
reg [31:0] REG [0:31];

//Write back
always @(posedge clk)//add new Dst REG source here
	if(MW_RD && MW_RegWrite)
	  REG[MW_RD] <= MW_ALUout;
	else
	  REG[MW_RD] <= REG[MW_RD];//keep REG[0] always equal zero

//set A, and other register content(j/beq flag and address)	
always @(posedge clk or posedge rst) begin
    if(rst) begin
        A 	<=32'b0;
    end 
    else begin
        A 	<=REG[IR[25:21]];
    end
end

//set control signal, choose Dst REG, and set B	
always @(posedge clk or posedge rst) begin
    if(rst) begin
        B 		<=32'b0;
        RD 		<=5'b0;
        ALUctr 	<=3'b0;
    end 
    else begin
        case(IR[31:26])
            6'd0://R-Type
            begin
                DX_RegWrite <= 1;
                Jump <= 0;
                case(IR[5:0])//funct & setting ALUctr
                    6'd32://add
                    begin
                        B	<=REG[IR[20:16]];
                        RD	<=IR[15:11];
                        ALUctr <=3'b010;//self define ALUctr value
                    end
                    6'd34://sub
                    begin
                        B	<=REG[IR[20:16]];
                        RD	<=IR[15:11];
                        ALUctr <=3'b110;//self define ALUctr value
                    end
                    6'b100100: // and
                    begin
                        B	<=REG[IR[20:16]];
                        RD	<=IR[15:11];
                        ALUctr <=3'b000;//self define ALUctr value
                    end
                    6'b100101: // or
                    begin
                        B	<=REG[IR[20:16]];
                        RD	<=IR[15:11];
                        ALUctr <=3'b001;//self define ALUctr value
                    end
                    6'd42://slt
                    begin
                        B	<=REG[IR[20:16]];
                        RD	<=IR[15:11];
                        ALUctr <= 3'b111;
                    end
                endcase
            end
            6'd35://lw
            begin
                Jump <= 0;
                Branch <= 0;
                DX_RegWrite <= 1;
            end
            6'd43://sw
            begin
                Jump <= 0;
                Branch <= 0;
                DX_RegWrite <= 0;
            end
            6'd4://beq
            begin
                Jump <= 0;
                Branch <= 1;
                DX_RegWrite <= 0;
            end
            6'd2://j
            begin
                Jump <= 1;
                JAddr <= {PC[31:28],IR[25:0],2'b0};
                Branch <= 0;
            end
        endcase
    end
end
endmodule

co/lab3/lab3-2/INSTRUCTION_FETCH.v
`timescale 1ns/1ps

module INSTRUCTION_FETCH(
	clk,
	rst,
    Jump,
    Branch,
    JAddr,

	PC,
	IR
);

input clk, rst;
input Jump;
input [31:0] JAddr;
input Branch;
output reg 	[31:0] PC, IR;

//instruction memory
reg [31:0] instruction [127:0];

//output instruction
always @(posedge clk or posedge rst) begin
	if(rst)
		IR <= 32'd0;
	else
		IR <= instruction[PC[10:2]];
end

// output program counter
always @(posedge clk or posedge rst) begin
	if(rst)
		PC <= 32'd0;
	else if (Jump)
		PC <= JAddr;
    else if (Branch)
		PC <= PC + 4;
    else
		PC <= PC + 4;
end

endmodule

co/lab3/lab3-2/CPU.v
`timescale 1ns/1ps

`include "INSTRUCTION_FETCH.v"
`include "INSTRUCTION_DECODE.v"
`include "EXECUTION.v"
`include "MEMORY.v"

module CPU(
	clk,
	rst
);
input clk, rst;
/*============================== Wire  ==============================*/
// INSTRUCTION_FETCH wires
wire [31:0] FD_PC, FD_IR;
// INSTRUCTION_DECODE wires
wire [31:0] A, B;
wire [4:0] DX_RD;
wire [2:0] ALUctr;
wire Jump;
wire [31:0] JAddr;
wire DX_Branch;
wire DX_RegWrite;
// EXECUTION wires
wire [31:0] XM_ALUout;
wire [4:0] XM_RD;
wire XF_Branch;
wire XM_RegWrite;
// DATA_MEMORY wires
wire [31:0] MW_ALUout;
wire [4:0]	MW_RD;
wire MW_RegWrite;

/*============================== INSTRUCTION_FETCH  ==============================*/

INSTRUCTION_FETCH IF(
	.clk(clk),
	.rst(rst),
    .Jump(Jump),
    .Branch(XF_Branch),
    .JAddr(JAddr),

	.PC(FD_PC),
	.IR(FD_IR)
);

/*============================== INSTRUCTION_DECODE ==============================*/

INSTRUCTION_DECODE ID(
	.clk(clk),
	.rst(rst),
	.PC(FD_PC),
	.IR(FD_IR),
	.MW_RD(MW_RD),
	.MW_ALUout(MW_ALUout),
    .MW_RegWrite(MW_RegWrite),

	.A(A),
	.B(B),
	.RD(DX_RD),
	.ALUctr(ALUctr),
    .Jump(Jump),
    .JAddr(JAddr),
    .Branch(DX_Branch),
    .DX_RegWrite(DX_RegWrite)
);

/*==============================     EXECUTION  	==============================*/

EXECUTION EXE(
	.clk(clk),
	.rst(rst),
	.A(A),
	.B(B),
	.DX_RD(DX_RD),
	.ALUctr(ALUctr),
    .DX_Branch(DX_Branch),
    .DX_RegWrite(DX_RegWrite),


	.ALUout(XM_ALUout),
	.XM_RD(XM_RD),
    .XF_Branch(XF_Branch),
    .XM_RegWrite(XM_RegWrite)
);

/*==============================     DATA_MEMORY	==============================*/

MEMORY MEM(
	.clk(clk),
	.rst(rst),
	.ALUout(XM_ALUout),
	.XM_RD(XM_RD),
    .XM_RegWrite(XM_RegWrite),

	.MW_ALUout(MW_ALUout),
	.MW_RD(MW_RD),
    .MW_RegWrite(MW_RegWrite)
);

endmodule

co/lab3/lab3-2/testbench.v
`define CYCLE_TIME 20
`define INSTRUCTION_NUMBERS 30
`timescale 1ns/1ps
`include "CPU.v"

module testbench;
reg Clk, Rst;
reg [31:0] cycles, i;

// Instruction DM initialilation
initial
begin
		//cpu.IF.instruction[ 0] = 32'b000000_00001_00010_00011_00000_100000;	//add $3, $1, $2
		cpu.IF.instruction[ 0] = 32'b000010_00000_00000_00000_00000_001010;	//jump 10
		cpu.IF.instruction[ 1] = 32'b000000_00000_00000_00000_00000_100000;	//NOP(add $0, $0, $0)
		cpu.IF.instruction[ 2] = 32'b000000_00000_00000_00000_00000_100000;	//NOP(add $0, $0, $0)
		cpu.IF.instruction[ 3] = 32'b000000_00000_00000_00000_00000_100000;	//NOP(add $0, $0, $0)
		cpu.IF.instruction[ 4] = 32'b000000_00000_00000_00000_00000_100000;	//NOP(add $0, $0, $0)

		cpu.IF.instruction[ 5] = 32'b000000_00001_00010_00100_00000_100010;	//sub $4, $1, $2
		cpu.IF.instruction[ 6] = 32'b000000_00000_00000_00000_00000_100000;	//NOP(add $0, $0, $0)
		cpu.IF.instruction[ 7] = 32'b000000_00000_00000_00000_00000_100000;	//NOP(add $0, $0, $0)
		cpu.IF.instruction[ 8] = 32'b000000_00000_00000_00000_00000_100000;	//NOP(add $0, $0, $0)
		cpu.IF.instruction[ 9] = 32'b000000_00000_00000_00000_00000_100000;	//NOP(add $0, $0, $0)

		cpu.IF.instruction[10] = 32'b000000_00001_00010_00101_00000_100100;	//and $5, $1, $2
		cpu.IF.instruction[11] = 32'b000000_00000_00000_00000_00000_100000;	//NOP(add $0, $0, $0)
		cpu.IF.instruction[12] = 32'b000000_00000_00000_00000_00000_100000;	//NOP(add $0, $0, $0)
		cpu.IF.instruction[13] = 32'b000000_00000_00000_00000_00000_100000;	//NOP(add $0, $0, $0)
		cpu.IF.instruction[14] = 32'b000000_00000_00000_00000_00000_100000;	//NOP(add $0, $0, $0)

		cpu.IF.instruction[15] = 32'b000000_00001_00010_00110_00000_100101;	//or $6, $1, $2
		cpu.IF.instruction[16] = 32'b000000_00000_00000_00000_00000_100000;	//NOP(add $0, $0, $0)
		cpu.IF.instruction[17] = 32'b000000_00000_00000_00000_00000_100000;	//NOP(add $0, $0, $0)
		cpu.IF.instruction[18] = 32'b000000_00000_00000_00000_00000_100000;	//NOP(add $0, $0, $0)
		cpu.IF.instruction[19] = 32'b000000_00000_00000_00000_00000_100000;	//NOP(add $0, $0, $0)

		cpu.IF.instruction[20] = 32'b000000_00001_00010_00111_00000_101010;	//slt $7, $1, $2
		cpu.IF.instruction[21] = 32'b000000_00000_00000_00000_00000_100000;	//NOP(add $0, $0, $0)
		cpu.IF.instruction[22] = 32'b000000_00000_00000_00000_00000_100000;	//NOP(add $0, $0, $0)
		cpu.IF.instruction[23] = 32'b000000_00000_00000_00000_00000_100000;	//NOP(add $0, $0, $0)
		cpu.IF.instruction[24] = 32'b000000_00000_00000_00000_00000_100000;	//NOP(add $0, $0, $0)

		cpu.IF.instruction[25] = 32'b000000_00000_00000_00000_00000_100000;	//NOP(add $0, $0, $0)
		cpu.IF.instruction[26] = 32'b000000_00000_00000_00000_00000_100000;	//NOP(add $0, $0, $0)
		cpu.IF.instruction[27] = 32'b000000_00000_00000_00000_00000_100000;	//NOP(add $0, $0, $0)
		cpu.IF.instruction[28] = 32'b000000_00000_00000_00000_00000_100000;	//NOP(add $0, $0, $0)
		cpu.IF.instruction[29] = 32'b000000_00000_00000_00000_00000_100000;	//NOP(add $0, $0, $0)

		cpu.IF.PC = 0;
end

// Data Memory & Register Files initialilation
initial
begin
	cpu.MEM.DM[0] = 32'd9;
	cpu.MEM.DM[1] = 32'd3;
	for (i=2; i<128; i=i+1) cpu.MEM.DM[i] = 32'b0;
	
	cpu.ID.REG[0] = 32'd0;
	cpu.ID.REG[1] = 32'd18;
	cpu.ID.REG[2] = 32'd25;
	for (i=3; i<32; i=i+1) cpu.ID.REG[i] = 32'b0;

end

//clock cycle time is 20ns, inverse Clk value per 10ns
initial Clk = 1'b1;
always #(`CYCLE_TIME/2) Clk = ~Clk;

//Rst signal
initial begin
	cycles = 32'b0;
	Rst = 1'b1;
	#12 Rst = 1'b0;
end

CPU cpu(
	.clk(Clk),
	.rst(Rst)
);

//display all Register value and Data memory content
always @(posedge Clk) begin
	cycles <= cycles + 1;
	if (cycles == `INSTRUCTION_NUMBERS) $finish; // Finish when excute the 24-th instruction (End label).
	$display("PC: %d cycles: %d", cpu.FD_PC>>2 , cycles);
	$display("  R00-R07: %08x %08x %08x %08x %08x %08x %08x %08x", cpu.ID.REG[0], cpu.ID.REG[1], cpu.ID.REG[2], cpu.ID.REG[3],cpu.ID.REG[4], cpu.ID.REG[5], cpu.ID.REG[6], cpu.ID.REG[7]);
	$display("  R08-R15: %08x %08x %08x %08x %08x %08x %08x %08x", cpu.ID.REG[8], cpu.ID.REG[9], cpu.ID.REG[10], cpu.ID.REG[11],cpu.ID.REG[12], cpu.ID.REG[13], cpu.ID.REG[14], cpu.ID.REG[15]);
	$display("  R16-R23: %08x %08x %08x %08x %08x %08x %08x %08x", cpu.ID.REG[16], cpu.ID.REG[17], cpu.ID.REG[18], cpu.ID.REG[19],cpu.ID.REG[20], cpu.ID.REG[21], cpu.ID.REG[22], cpu.ID.REG[23]);
	$display("  R24-R31: %08x %08x %08x %08x %08x %08x %08x %08x", cpu.ID.REG[24], cpu.ID.REG[25], cpu.ID.REG[26], cpu.ID.REG[27],cpu.ID.REG[28], cpu.ID.REG[29], cpu.ID.REG[30], cpu.ID.REG[31]);
	$display("  0x00   : %08x %08x %08x %08x %08x %08x %08x %08x", cpu.MEM.DM[0],cpu.MEM.DM[1],cpu.MEM.DM[2],cpu.MEM.DM[3],cpu.MEM.DM[4],cpu.MEM.DM[5],cpu.MEM.DM[6],cpu.MEM.DM[7]);
	$display("  0x08   : %08x %08x %08x %08x %08x %08x %08x %08x", cpu.MEM.DM[8],cpu.MEM.DM[9],cpu.MEM.DM[10],cpu.MEM.DM[11],cpu.MEM.DM[12],cpu.MEM.DM[13],cpu.MEM.DM[14],cpu.MEM.DM[15]);
end

//generate wave file, it can use gtkwave to display
initial begin
	$dumpfile("cpu_hw.vcd");
	$dumpvars;
end
endmodule

co/lab3/lab3-2/cpu_hw.vcd
$date
	Sun Dec 17 15:19:59 2017
$end
$version
	Icarus Verilog
$end
$timescale
	1ps
$end
$scope module testbench $end
$var reg 1 ! Clk $end
$var reg 1 " Rst $end
$var reg 32 # cycles [31:0] $end
$var reg 32 $ i [31:0] $end
$scope module cpu $end
$var wire 1 ! clk $end
$var wire 1 " rst $end
$var wire 1 % XM_RegWrite $end
$var wire 5 & XM_RD [4:0] $end
$var wire 32 ' XM_ALUout [31:0] $end
$var wire 1 ( XF_Branch $end
$var wire 1 ) MW_RegWrite $end
$var wire 5 * MW_RD [4:0] $end
$var wire 32 + MW_ALUout [31:0] $end
$var wire 1 , Jump $end
$var wire 32 - JAddr [31:0] $end
$var wire 32 . FD_PC [31:0] $end
$var wire 32 / FD_IR [31:0] $end
$var wire 1 0 DX_RegWrite $end
$var wire 5 1 DX_RD [4:0] $end
$var wire 1 2 DX_Branch $end
$var wire 32 3 B [31:0] $end
$var wire 3 4 ALUctr [2:0] $end
$var wire 32 5 A [31:0] $end
$scope module EXE $end
$var wire 1 6 ALUop $end
$var wire 1 ! clk $end
$var wire 1 " rst $end
$var wire 1 0 DX_RegWrite $end
$var wire 5 7 DX_RD [4:0] $end
$var wire 1 2 DX_Branch $end
$var wire 32 8 B [31:0] $end
$var wire 3 9 ALUctr [2:0] $end
$var wire 32 : A [31:0] $end
$var reg 32 ; ALUout [31:0] $end
$var reg 1 ( XF_Branch $end
$var reg 5 < XM_RD [4:0] $end
$var reg 1 % XM_RegWrite $end
$upscope $end
$scope module ID $end
$var wire 1 ! clk $end
$var wire 1 " rst $end
$var wire 32 = PC [31:0] $end
$var wire 1 ) MW_RegWrite $end
$var wire 5 > MW_RD [4:0] $end
$var wire 32 ? MW_ALUout [31:0] $end
$var wire 32 @ IR [31:0] $end
$var reg 32 A A [31:0] $end
$var reg 3 B ALUctr [2:0] $end
$var reg 32 C B [31:0] $end
$var reg 1 2 Branch $end
$var reg 1 0 DX_RegWrite $end
$var reg 32 D JAddr [31:0] $end
$var reg 1 , Jump $end
$var reg 5 E RD [4:0] $end
$upscope $end
$scope module IF $end
$var wire 1 ( Branch $end
$var wire 32 F JAddr [31:0] $end
$var wire 1 , Jump $end
$var wire 1 ! clk $end
$var wire 1 " rst $end
$var reg 32 G IR [31:0] $end
$var reg 32 H PC [31:0] $end
$upscope $end
$scope module MEM $end
$var wire 32 I ALUout [31:0] $end
$var wire 5 J XM_RD [4:0] $end
$var wire 1 % XM_RegWrite $end
$var wire 1 ! clk $end
$var wire 1 " rst $end
$var reg 32 K MW_ALUout [31:0] $end
$var reg 5 L MW_RD [4:0] $end
$var reg 1 ) MW_RegWrite $end
$upscope $end
$upscope $end
$upscope $end
$enddefinitions $end
#0
$dumpvars
b0 L
b0 K
b0 J
b0 I
b0 H
b0 G
bx F
b0 E
bx D
b0 C
b0 B
b0 A
b0 @
b0 ?
b0 >
b0 =
b0 <
b0 ;
b0 :
b0 9
b0 8
b0 7
z6
b0 5
b0 4
b0 3
x2
b0 1
x0
b0 /
b0 .
bx -
x,
b0 +
b0 *
0)
0(
b0 '
b0 &
0%
b100000 $
b0 #
1"
1!
$end
#10000
0!
#12000
0"
#20000
x%
x(
0,
10
b100 .
b100 =
b100 H
b1000000000000000000000001010 /
b1000000000000000000000001010 @
b1000000000000000000000001010 G
b1 #
1!
#30000
0!
#40000
b100000 /
b100000 @
b100000 G
b1000 .
b1000 =
b1000 H
02
b101000 -
b101000 D
b101000 F
1,
1%
x)
b10 #
1!
#50000
0!
#60000
0(
b10 4
b10 9
b10 B
0,
b101000 .
b101000 =
b101000 H
b11 #
1)
1!
#70000
0!
#80000
b1000100010100000100100 /
b1000100010100000100100 @
b1000100010100000100100 G
b101100 .
b101100 =
b101100 H
b100 #
1!
#90000
0!
#100000
b0 4
b0 9
b0 B
b101 1
b101 7
b101 E
b11001 3
b11001 8
b11001 C
b10010 5
b10010 :
b10010 A
b110000 .
b110000 =
b110000 H
b100000 /
b100000 @
b100000 G
b101 #
1!
#110000
0!
#120000
b110100 .
b110100 =
b110100 H
b0 5
b0 :
b0 A
b10 4
b10 9
b10 B
b0 1
b0 7
b0 E
b0 3
b0 8
b0 C
b101 &
b101 <
b101 J
b10000 '
b10000 ;
b10000 I
b110 #
1!
#130000
0!
#140000
b0 '
b0 ;
b0 I
b0 &
b0 <
b0 J
b111000 .
b111000 =
b111000 H
b111 #
b101 *
b101 >
b101 L
b10000 +
b10000 ?
b10000 K
1!
#150000
0!
#160000
b111100 .
b111100 =
b111100 H
b0 *
b0 >
b0 L
b0 +
b0 ?
b0 K
b1000 #
1!
#170000
0!
#180000
b1000000 .
b1000000 =
b1000000 H
b1000100011000000100101 /
b1000100011000000100101 @
b1000100011000000100101 G
b1001 #
1!
#190000
0!
#200000
b100000 /
b100000 @
b100000 G
b1000100 .
b1000100 =
b1000100 H
b10010 5
b10010 :
b10010 A
b1 4
b1 9
b1 B
b110 1
b110 7
b110 E
b11001 3
b11001 8
b11001 C
b1010 #
1!
#210000
0!
#220000
b11011 '
b11011 ;
b11011 I
b110 &
b110 <
b110 J
b10 4
b10 9
b10 B
b0 1
b0 7
b0 E
b0 3
b0 8
b0 C
b0 5
b0 :
b0 A
b1001000 .
b1001000 =
b1001000 H
b1011 #
1!
#230000
0!
#240000
b1001100 .
b1001100 =
b1001100 H
b0 &
b0 <
b0 J
b0 '
b0 ;
b0 I
b110 *
b110 >
b110 L
b11011 +
b11011 ?
b11011 K
b1100 #
1!
#250000
0!
#260000
b1010000 .
b1010000 =
b1010000 H
b1101 #
b0 *
b0 >
b0 L
b0 +
b0 ?
b0 K
1!
#270000
0!
#280000
b1000100011100000101010 /
b1000100011100000101010 @
b1000100011100000101010 G
b1010100 .
b1010100 =
b1010100 H
b1110 #
1!
#290000
0!
#300000
b111 4
b111 9
b111 B
b111 1
b111 7
b111 E
b11001 3
b11001 8
b11001 C
b10010 5
b10010 :
b10010 A
b1011000 .
b1011000 =
b1011000 H
b100000 /
b100000 @
b100000 G
b1111 #
1!
#310000
0!
#320000
b1011100 .
b1011100 =
b1011100 H
b0 5
b0 :
b0 A
b10 4
b10 9
b10 B
b0 1
b0 7
b0 E
b0 3
b0 8
b0 C
b111 &
b111 <
b111 J
b1 '
b1 ;
b1 I
b10000 #
1!
#330000
0!
#340000
b0 '
b0 ;
b0 I
b0 &
b0 <
b0 J
b1100000 .
b1100000 =
b1100000 H
b10001 #
b111 *
b111 >
b111 L
b1 +
b1 ?
b1 K
1!
#350000
0!
#360000
b1100100 .
b1100100 =
b1100100 H
b0 *
b0 >
b0 L
b0 +
b0 ?
b0 K
b10010 #
1!
#370000
0!
#380000
b1101000 .
b1101000 =
b1101000 H
b10011 #
1!
#390000
0!
#400000
b1101100 .
b1101100 =
b1101100 H
b10100 #
1!
#410000
0!
#420000
b1110000 .
b1110000 =
b1110000 H
b10101 #
1!
#430000
0!
#440000
b1110100 .
b1110100 =
b1110100 H
b10110 #
1!
#450000
0!
#460000
b1111000 .
b1111000 =
b1111000 H
b10111 #
1!
#470000
0!
#480000
bx /
bx @
bx G
b1111100 .
b1111100 =
b1111100 H
b11000 #
1!
#490000
0!
#500000
bx 5
bx :
bx A
b10000000 .
b10000000 =
b10000000 H
b11001 #
1!
#510000
0!
#520000
b10000100 .
b10000100 =
b10000100 H
bx '
bx ;
bx I
b11010 #
1!
#530000
0!
#540000
b10001000 .
b10001000 =
b10001000 H
b11011 #
bx +
bx ?
bx K
1!
#550000
0!
#560000
b10001100 .
b10001100 =
b10001100 H
b11100 #
1!
#570000
0!
#580000
b10010000 .
b10010000 =
b10010000 H
b11101 #
1!
#590000
0!
#600000
b10010100 .
b10010100 =
b10010100 H
b11110 #
1!
#610000
0!
#620000
b10011000 .
b10011000 =
b10011000 H
b11111 #
1!
