co/lab3/lab3-2/MEMORY.v
`timescale 1ns/1ps

module MEMORY(
	clk, rst,
	XM_RD,
	ALUout,
    XM_RegWrite,

	MW_RD,
	MW_ALUout,
    MW_RegWrite
);
input clk, rst;
input [4:0] XM_RD;
input [31:0] ALUout;
input XM_RegWrite;

output reg [4:0] MW_RD;
output reg [31:0] MW_ALUout;
output reg MW_RegWrite;

//data memory
reg [31:0] DM [0:127];
/*
//always store word to data memory
always @(posedge clk)
  if(XM_MemWrite)
    DM[ALUout[6:0]] <= XM_MD;
*/

//send to Dst REG: "load word from data memory" or  "ALUout"
always @(posedge clk) begin
    if(rst) begin
        MW_ALUout	<=	32'b0;
        MW_RD		<=	5'b0;
        MW_RegWrite <= 0;
    end
    else begin
        MW_ALUout	<=	ALUout;
        MW_RD		<=	XM_RD;
        MW_RegWrite <= XM_RegWrite;
    end
end

endmodule

co/lab3/lab3-2/EXECUTION.v
`timescale 1ns/1ps

module EXECUTION(
    clk, rst,
    DX_PC,
    DX_RD,
    A, B, Imm,
    ALUctr,
    ALUSrc,
    DX_Branch,
    DX_RegWrite,

    XM_RD,
    ALUout, BAddr,
    XF_Branch,
    XM_RegWrite
);

input clk, rst;
input [31:0] DX_PC;
input [4:0] DX_RD;
input [31:0] A, B, Imm;
input [2:0] ALUctr;
input ALUSrc;
input DX_Branch;
input DX_RegWrite;

output reg [4:0] XM_RD;
output reg [31:0] ALUout, BAddr;
output reg XF_Branch;
output reg XM_RegWrite;

//set pipeline register
always @(posedge clk or posedge rst) begin
    if(rst) begin
        XM_RD       <= 5'd0;
        XF_Branch   <= 1'b0;
        XM_RegWrite <= 1'b0;
        BAddr       <= 1'b0;
    end 
    else begin
        XM_RD       <= DX_RD;
        XF_Branch   <= DX_Branch && (A==B);
        XM_RegWrite <= DX_RegWrite;
        BAddr       <= DX_PC + (Imm<<2);
    end
end

// calculating ALUout
always @(posedge clk or posedge rst) begin
    if(rst) begin
        ALUout	<= 32'd0;
    end 
    else begin
        case(ALUctr)
            3'b010: //add //lw //sw
            begin
                ALUout <= (ALUSrc)? A+Imm: A+B;
            end
            3'b110: //sub
            begin
                ALUout <= (ALUSrc)? A-Imm: A-B;
            end
            3'b000: // and
            begin
                ALUout <= A & B;
            end
            3'b001: // or
            begin
                ALUout <= A | B;
            end
            3'b111: // slt
            begin
                ALUout <= (A < B)? 1: 0;
            end
        endcase
    end
end
endmodule

co/lab3/lab3-2/INSTRUCTION_DECODE.v
`timescale 1ns/1ps

module INSTRUCTION_DECODE(
	clk, rst,
	PC, IR,
	MW_ALUout,
	MW_RD,
    MW_RegWrite,

    DX_PC,
	RD,
	A, B, Imm, JAddr,
	ALUctr,
    ALUSrc,
    Jump,
    Branch,
    DX_RegWrite
);

input clk,rst;
input [31:0] PC, IR, MW_ALUout;
input [4:0] MW_RD;
input MW_RegWrite;

output reg [31:0] DX_PC;
output reg [4:0] RD;
output reg [31:0] A, B, Imm, JAddr;
output reg [2:0] ALUctr;
output reg ALUSrc;
output reg Jump;
output reg Branch;
output reg DX_RegWrite;

//register file
reg [31:0] REG [0:31];

//Write back
always @(posedge clk)//add new Dst REG source here
	if(MW_RD && MW_RegWrite)
	  REG[MW_RD] <= MW_ALUout;
	else
	  REG[MW_RD] <= REG[MW_RD];//keep REG[0] always equal zero

//set A, and other register content(j/beq flag and address)	
always @(posedge clk or posedge rst) begin
    if(rst) begin
        DX_PC   <= 32'b0;
        A 	    <= 32'b0;
        B 	    <= 32'b0;
        Imm	    <= 32'b0;
        JAddr 	<= 32'b0;
    end 
    else begin
        DX_PC   <= PC;
        A    	<= REG[IR[25:21]];
        B   	<= REG[IR[20:16]];
        Imm     <= {16'b0, IR[15:0]};
        JAddr   <= {PC[31:28], IR[25:0], 2'b0};
    end
end

//set control signal, choose Dst REG, and set B	
always @(posedge clk or posedge rst) begin
    if(rst) begin
        ALUctr 	<= 3'b0;
        Jump    <= 1'b0;
        Branch  <= 1'b0;
        DX_RegWrite <= 1'b0;
        RD 		<= 5'b0;
    end 
    else begin
        case(IR[31:26])
            6'd0://R-Type
            begin
                ALUSrc      <= 1'b0;
                Jump        <= 1'b0;
                Branch      <= 1'b0;
                DX_RegWrite <= 1'b1;
                RD	<=IR[15:11];
                case(IR[5:0])//funct & setting ALUctr
                    6'b100000: ALUctr <= 3'b010; //add
                    6'b100010: ALUctr <= 3'b110; //sub
                    6'b100100: ALUctr <= 3'b000; // and
                    6'b100101: ALUctr <= 3'b001; // or
                    6'b101010: ALUctr <= 3'b111; //slt
                endcase
            end
            6'b001000: // addi
            begin
                ALUSrc      <= 1'b1;
                ALUctr      <= 3'b010;
                Jump        <= 1'b0;
                Branch      <= 1'b0;
                DX_RegWrite <= 1'b1;
                RD          <= IR[20:16];
            end
            6'd35://lw
            begin
                ALUSrc      <= 1'b1;
                Jump <= 0;
                Branch <= 0;
                DX_RegWrite <= 1;
                RD  <= IR[20:16];
            end
            6'd43://sw
            begin
                ALUSrc      <= 1'b1;
                Jump <= 0;
                Branch <= 0;
                DX_RegWrite <= 0;
                RD  <= IR[20:16];
            end
            6'b000100://beq
            begin
                ALUSrc      <= 1'b0;
                ALUctr      <= 3'b110;
                Jump <= 0;
                Branch <= 1;
                DX_RegWrite <= 0;
                RD <= IR[20:16];
            end
            6'd2://j
            begin
                Jump <= 1;
                Branch <= 0;
            end
        endcase
    end
end
endmodule

co/lab3/lab3-2/INSTRUCTION_FETCH.v
`timescale 1ns/1ps

module INSTRUCTION_FETCH(
	clk, rst,
    Jump, Branch,
    JAddr, BAddr,

	PC, IR
);

input clk, rst;
input Jump, Branch;
input [31:0] JAddr, BAddr;

output reg 	[31:0] PC, IR;

//instruction memory
reg [31:0] instruction [127:0];

//output instruction
always @(posedge clk or posedge rst) begin
	if(rst)
		IR <= 32'd0;
	else
		IR <= instruction[PC[10:2]];
end

// output program counter
always @(posedge clk or posedge rst) begin
	if(rst)
		PC <= 32'd0;
	else
        PC <= (Jump)? JAddr: (Branch)? BAddr: PC+4;
end

endmodule

co/lab3/lab3-2/CPU.v
`timescale 1ns/1ps

`include "INSTRUCTION_FETCH.v"
`include "INSTRUCTION_DECODE.v"
`include "EXECUTION.v"
`include "MEMORY.v"

module CPU(
	clk,
	rst
);
input clk, rst;
/*============================== Wire  ==============================*/
// INSTRUCTION_FETCH wires
wire [31:0] FD_PC, FD_IR;
// INSTRUCTION_DECODE wires
wire [31:0] DX_PC;
wire [4:0] DX_RD;
wire [31:0] A, B, Imm, JAddr;
wire [2:0] ALUctr;
wire ALUSrc;
wire Jump;
wire DX_Branch;
wire DX_RegWrite;
// EXECUTION wires
wire [4:0] XM_RD;
wire [31:0] XM_ALUout, BAddr;
wire XF_Branch;
wire XM_RegWrite;
// DATA_MEMORY wires
wire [4:0]	MW_RD;
wire [31:0] MW_ALUout;
wire MW_RegWrite;

/*============================== INSTRUCTION_FETCH  ==============================*/

INSTRUCTION_FETCH IF(
	.clk(clk),
	.rst(rst),
    .Jump(Jump),
    .JAddr(JAddr),
    .Branch(XF_Branch),
    .BAddr(BAddr),

	.PC(FD_PC),
	.IR(FD_IR)
);

/*============================== INSTRUCTION_DECODE ==============================*/

INSTRUCTION_DECODE ID(
	.clk(clk),
	.rst(rst),
	.PC(FD_PC),
	.IR(FD_IR),
	.MW_RD(MW_RD),
	.MW_ALUout(MW_ALUout),
    .MW_RegWrite(MW_RegWrite),

    .DX_PC(DX_PC),
	.RD(DX_RD),
	.A(A),
	.B(B),
    .Imm(Imm),
    .JAddr(JAddr),
	.ALUctr(ALUctr),
    .ALUSrc(ALUSrc),
    .Jump(Jump),
    .Branch(DX_Branch),
    .DX_RegWrite(DX_RegWrite)
);

/*==============================     EXECUTION  	==============================*/

EXECUTION EXE(
	.clk(clk),
	.rst(rst),
	.A(A),
	.B(B),
    .Imm(Imm),
    .DX_PC(DX_PC),
	.DX_RD(DX_RD),
	.ALUctr(ALUctr),
    .ALUSrc(ALUSrc),
    .DX_Branch(DX_Branch),
    .DX_RegWrite(DX_RegWrite),


	.ALUout(XM_ALUout),
    .BAddr(BAddr),
	.XM_RD(XM_RD),
    .XF_Branch(XF_Branch),
    .XM_RegWrite(XM_RegWrite)
);

/*==============================     DATA_MEMORY	==============================*/

MEMORY MEM(
	.clk(clk),
	.rst(rst),
	.XM_RD(XM_RD),
	.ALUout(XM_ALUout),
    .XM_RegWrite(XM_RegWrite),

	.MW_RD(MW_RD),
	.MW_ALUout(MW_ALUout),
    .MW_RegWrite(MW_RegWrite)
);

endmodule

co/lab3/lab3-2/testbench.v
`define CYCLE_TIME 20
`define INSTRUCTION_NUMBERS 35
`timescale 1ns/1ps
`include "CPU.v"

module testbench;
reg Clk, Rst;
reg [31:0] cycles, i;

// Instruction DM initialilation
initial
begin
		cpu.IF.instruction[ 0] = 32'b000000_00001_00010_00011_00000_100000;	//add $3, $1, $2
		//cpu.IF.instruction[ 0] = 32'b000010_00000_00000_00000_00000_001111;	//jump 15
		cpu.IF.instruction[ 1] = 32'b000000_00000_00000_00000_00000_100000;	//NOP(add $0, $0, $0)
		cpu.IF.instruction[ 2] = 32'b000000_00000_00000_00000_00000_100000;	//NOP(add $0, $0, $0)
		cpu.IF.instruction[ 3] = 32'b000000_00000_00000_00000_00000_100000;	//NOP(add $0, $0, $0)
		cpu.IF.instruction[ 4] = 32'b000000_00000_00000_00000_00000_100000;	//NOP(add $0, $0, $0)

		cpu.IF.instruction[ 5] = 32'b000000_00001_00010_00100_00000_100010;	//sub $4, $1, $2
		//cpu.IF.instruction[ 5] = 32'b000100_00001_00010_00000_00000_001001;	//beq $1, $2, 9
		cpu.IF.instruction[ 6] = 32'b000000_00000_00000_00000_00000_100000;	//NOP(add $0, $0, $0)
		cpu.IF.instruction[ 7] = 32'b000000_00000_00000_00000_00000_100000;	//NOP(add $0, $0, $0)
		cpu.IF.instruction[ 8] = 32'b000000_00000_00000_00000_00000_100000;	//NOP(add $0, $0, $0)
		cpu.IF.instruction[ 9] = 32'b000000_00000_00000_00000_00000_100000;	//NOP(add $0, $0, $0)

		cpu.IF.instruction[10] = 32'b000000_00001_00010_00101_00000_100100;	//and $5, $1, $2
		cpu.IF.instruction[11] = 32'b000000_00000_00000_00000_00000_100000;	//NOP(add $0, $0, $0)
		cpu.IF.instruction[12] = 32'b000000_00000_00000_00000_00000_100000;	//NOP(add $0, $0, $0)
		cpu.IF.instruction[13] = 32'b000000_00000_00000_00000_00000_100000;	//NOP(add $0, $0, $0)
		cpu.IF.instruction[14] = 32'b000000_00000_00000_00000_00000_100000;	//NOP(add $0, $0, $0)

		cpu.IF.instruction[15] = 32'b000000_00001_00010_00110_00000_100101;	//or $6, $1, $2
		cpu.IF.instruction[16] = 32'b000000_00000_00000_00000_00000_100000;	//NOP(add $0, $0, $0)
		cpu.IF.instruction[17] = 32'b000000_00000_00000_00000_00000_100000;	//NOP(add $0, $0, $0)
		cpu.IF.instruction[18] = 32'b000000_00000_00000_00000_00000_100000;	//NOP(add $0, $0, $0)
		cpu.IF.instruction[19] = 32'b000000_00000_00000_00000_00000_100000;	//NOP(add $0, $0, $0)

		cpu.IF.instruction[20] = 32'b000000_00001_00010_00111_00000_101010;	//slt $7, $1, $2
		cpu.IF.instruction[21] = 32'b000000_00000_00000_00000_00000_100000;	//NOP(add $0, $0, $0)
		cpu.IF.instruction[22] = 32'b000000_00000_00000_00000_00000_100000;	//NOP(add $0, $0, $0)
		cpu.IF.instruction[23] = 32'b000000_00000_00000_00000_00000_100000;	//NOP(add $0, $0, $0)
		cpu.IF.instruction[24] = 32'b000000_00000_00000_00000_00000_100000;	//NOP(add $0, $0, $0)

		cpu.IF.instruction[25] = 32'b001000_00001_01000_00000_00000_000110;	//addi $8, $1, 6
		cpu.IF.instruction[26] = 32'b000000_00000_00000_00000_00000_100000;	//NOP(add $0, $0, $0)
		cpu.IF.instruction[27] = 32'b000000_00000_00000_00000_00000_100000;	//NOP(add $0, $0, $0)
		cpu.IF.instruction[28] = 32'b000000_00000_00000_00000_00000_100000;	//NOP(add $0, $0, $0)
		cpu.IF.instruction[29] = 32'b000000_00000_00000_00000_00000_100000;	//NOP(add $0, $0, $0)

		cpu.IF.instruction[30] = 32'b000000_00000_00000_00000_00000_100000;	//NOP(add $0, $0, $0)
		cpu.IF.instruction[31] = 32'b000000_00000_00000_00000_00000_100000;	//NOP(add $0, $0, $0)
		cpu.IF.instruction[32] = 32'b000000_00000_00000_00000_00000_100000;	//NOP(add $0, $0, $0)
		cpu.IF.instruction[33] = 32'b000000_00000_00000_00000_00000_100000;	//NOP(add $0, $0, $0)
		cpu.IF.instruction[34] = 32'b000000_00000_00000_00000_00000_100000;	//NOP(add $0, $0, $0)

		cpu.IF.PC = 0;
end

// Data Memory & Register Files initialilation
initial
begin
	cpu.MEM.DM[0] = 32'd9;
	cpu.MEM.DM[1] = 32'd3;
	for (i=2; i<128; i=i+1) cpu.MEM.DM[i] = 32'b0;
	
	cpu.ID.REG[0] = 32'd0;
	cpu.ID.REG[1] = 32'd25;
	cpu.ID.REG[2] = 32'd25;
	for (i=3; i<32; i=i+1) cpu.ID.REG[i] = 32'b0;

end

//clock cycle time is 20ns, inverse Clk value per 10ns
initial Clk = 1'b1;
always #(`CYCLE_TIME/2) Clk = ~Clk;

//Rst signal
initial begin
	cycles = 32'b0;
	Rst = 1'b1;
	#12 Rst = 1'b0;
end

CPU cpu(
	.clk(Clk),
	.rst(Rst)
);

//display all Register value and Data memory content
always @(posedge Clk) begin
	cycles <= cycles + 1;
	if (cycles == `INSTRUCTION_NUMBERS) $finish; // Finish when excute the 24-th instruction (End label).
	$display("PC: %d cycles: %d", cpu.FD_PC>>2 , cycles);
	$display("  R00-R07: %08x %08x %08x %08x %08x %08x %08x %08x", cpu.ID.REG[0], cpu.ID.REG[1], cpu.ID.REG[2], cpu.ID.REG[3],cpu.ID.REG[4], cpu.ID.REG[5], cpu.ID.REG[6], cpu.ID.REG[7]);
	$display("  R08-R15: %08x %08x %08x %08x %08x %08x %08x %08x", cpu.ID.REG[8], cpu.ID.REG[9], cpu.ID.REG[10], cpu.ID.REG[11],cpu.ID.REG[12], cpu.ID.REG[13], cpu.ID.REG[14], cpu.ID.REG[15]);
	$display("  R16-R23: %08x %08x %08x %08x %08x %08x %08x %08x", cpu.ID.REG[16], cpu.ID.REG[17], cpu.ID.REG[18], cpu.ID.REG[19],cpu.ID.REG[20], cpu.ID.REG[21], cpu.ID.REG[22], cpu.ID.REG[23]);
	$display("  R24-R31: %08x %08x %08x %08x %08x %08x %08x %08x", cpu.ID.REG[24], cpu.ID.REG[25], cpu.ID.REG[26], cpu.ID.REG[27],cpu.ID.REG[28], cpu.ID.REG[29], cpu.ID.REG[30], cpu.ID.REG[31]);
	$display("  0x00   : %08x %08x %08x %08x %08x %08x %08x %08x", cpu.MEM.DM[0],cpu.MEM.DM[1],cpu.MEM.DM[2],cpu.MEM.DM[3],cpu.MEM.DM[4],cpu.MEM.DM[5],cpu.MEM.DM[6],cpu.MEM.DM[7]);
	$display("  0x08   : %08x %08x %08x %08x %08x %08x %08x %08x", cpu.MEM.DM[8],cpu.MEM.DM[9],cpu.MEM.DM[10],cpu.MEM.DM[11],cpu.MEM.DM[12],cpu.MEM.DM[13],cpu.MEM.DM[14],cpu.MEM.DM[15]);
end

//generate wave file, it can use gtkwave to display
initial begin
	$dumpfile("cpu_hw.vcd");
	$dumpvars;
end
endmodule

co/lab3/lab3-2/cpu_hw.vcd
$date
	Sun Dec 17 18:35:29 2017
$end
$version
	Icarus Verilog
$end
$timescale
	1ps
$end
$scope module testbench $end
$var reg 1 ! Clk $end
$var reg 1 " Rst $end
$var reg 32 # cycles [31:0] $end
$var reg 32 $ i [31:0] $end
$scope module cpu $end
$var wire 1 ! clk $end
$var wire 1 " rst $end
$var wire 1 % XM_RegWrite $end
$var wire 5 & XM_RD [4:0] $end
$var wire 32 ' XM_ALUout [31:0] $end
$var wire 1 ( XF_Branch $end
$var wire 1 ) MW_RegWrite $end
$var wire 5 * MW_RD [4:0] $end
$var wire 32 + MW_ALUout [31:0] $end
$var wire 1 , Jump $end
$var wire 32 - JAddr [31:0] $end
$var wire 32 . Imm [31:0] $end
$var wire 32 / FD_PC [31:0] $end
$var wire 32 0 FD_IR [31:0] $end
$var wire 1 1 DX_RegWrite $end
$var wire 5 2 DX_RD [4:0] $end
$var wire 32 3 DX_PC [31:0] $end
$var wire 1 4 DX_Branch $end
$var wire 32 5 BAddr [31:0] $end
$var wire 32 6 B [31:0] $end
$var wire 3 7 ALUctr [2:0] $end
$var wire 1 8 ALUSrc $end
$var wire 32 9 A [31:0] $end
$scope module EXE $end
$var wire 1 ! clk $end
$var wire 1 " rst $end
$var wire 32 : Imm [31:0] $end
$var wire 1 1 DX_RegWrite $end
$var wire 5 ; DX_RD [4:0] $end
$var wire 32 < DX_PC [31:0] $end
$var wire 1 4 DX_Branch $end
$var wire 32 = B [31:0] $end
$var wire 3 > ALUctr [2:0] $end
$var wire 1 8 ALUSrc $end
$var wire 32 ? A [31:0] $end
$var reg 32 @ ALUout [31:0] $end
$var reg 32 A BAddr [31:0] $end
$var reg 1 ( XF_Branch $end
$var reg 5 B XM_RD [4:0] $end
$var reg 1 % XM_RegWrite $end
$upscope $end
$scope module ID $end
$var wire 1 ! clk $end
$var wire 1 " rst $end
$var wire 32 C PC [31:0] $end
$var wire 1 ) MW_RegWrite $end
$var wire 5 D MW_RD [4:0] $end
$var wire 32 E MW_ALUout [31:0] $end
$var wire 32 F IR [31:0] $end
$var reg 32 G A [31:0] $end
$var reg 1 8 ALUSrc $end
$var reg 3 H ALUctr [2:0] $end
$var reg 32 I B [31:0] $end
$var reg 1 4 Branch $end
$var reg 32 J DX_PC [31:0] $end
$var reg 1 1 DX_RegWrite $end
$var reg 32 K Imm [31:0] $end
$var reg 32 L JAddr [31:0] $end
$var reg 1 , Jump $end
$var reg 5 M RD [4:0] $end
$upscope $end
$scope module IF $end
$var wire 32 N BAddr [31:0] $end
$var wire 1 ( Branch $end
$var wire 32 O JAddr [31:0] $end
$var wire 1 , Jump $end
$var wire 1 ! clk $end
$var wire 1 " rst $end
$var reg 32 P IR [31:0] $end
$var reg 32 Q PC [31:0] $end
$upscope $end
$scope module MEM $end
$var wire 32 R ALUout [31:0] $end
$var wire 5 S XM_RD [4:0] $end
$var wire 1 % XM_RegWrite $end
$var wire 1 ! clk $end
$var wire 1 " rst $end
$var reg 32 T MW_ALUout [31:0] $end
$var reg 5 U MW_RD [4:0] $end
$var reg 1 ) MW_RegWrite $end
$upscope $end
$upscope $end
$upscope $end
$enddefinitions $end
#0
$dumpvars
b0 U
b0 T
b0 S
b0 R
b0 Q
b0 P
b0 O
b0 N
b0 M
b0 L
b0 K
b0 J
b0 I
b0 H
b0 G
b0 F
b0 E
b0 D
b0 C
b0 B
b0 A
b0 @
b0 ?
b0 >
b0 =
b0 <
b0 ;
b0 :
b0 9
x8
b0 7
b0 6
b0 5
04
b0 3
b0 2
01
b0 0
b0 /
b0 .
b0 -
0,
b0 +
b0 *
0)
0(
b0 '
b0 &
0%
b100000 $
b0 #
1"
1!
$end
#10000
0!
#12000
0"
#20000
11
08
b100 /
b100 C
b100 Q
b1000100001100000100000 0
b1000100001100000100000 F
b1000100001100000100000 P
b1 #
1!
#30000
0!
#40000
b100000 0
b100000 F
b100000 P
b1000 /
b1000 C
b1000 Q
b100010000110000010000000 -
b100010000110000010000000 L
b100010000110000010000000 O
b1100000100000 .
b1100000100000 :
b1100000100000 K
b11001 6
b11001 =
b11001 I
b11001 9
b11001 ?
b11001 G
b100 3
b100 <
b100 J
b10 7
b10 >
b10 H
b11 2
b11 ;
b11 M
1%
b10 #
1!
#50000
0!
#60000
b110010 '
b110010 @
b110010 R
b110000010000100 5
b110000010000100 A
b110000010000100 N
b11 &
b11 B
b11 S
b0 2
b0 ;
b0 M
b10000000 -
b10000000 L
b10000000 O
b100000 .
b100000 :
b100000 K
b0 6
b0 =
b0 I
b0 9
b0 ?
b0 G
b1000 3
b1000 <
b1000 J
b1100 /
b1100 C
b1100 Q
b11 #
1)
1!
#70000
0!
#80000
b10000 /
b10000 C
b10000 Q
b1100 3
b1100 <
b1100 J
b10001000 5
b10001000 A
b10001000 N
b0 &
b0 B
b0 S
b0 '
b0 @
b0 R
b11 *
b11 D
b11 U
b110010 +
b110010 E
b110010 T
b100 #
1!
#90000
0!
#100000
b10001100 5
b10001100 A
b10001100 N
b10000 3
b10000 <
b10000 J
b10100 /
b10100 C
b10100 Q
b101 #
b0 *
b0 D
b0 U
b0 +
b0 E
b0 T
1!
#110000
0!
#120000
b1000100010000000100010 0
b1000100010000000100010 F
b1000100010000000100010 P
b11000 /
b11000 C
b11000 Q
b10100 3
b10100 <
b10100 J
b10010000 5
b10010000 A
b10010000 N
b110 #
1!
#130000
0!
#140000
b10010100 5
b10010100 A
b10010100 N
b110 7
b110 >
b110 H
b100 2
b100 ;
b100 M
b100010001000000010001000 -
b100010001000000010001000 L
b100010001000000010001000 O
b10000000100010 .
b10000000100010 :
b10000000100010 K
b11001 6
b11001 =
b11001 I
b11001 9
b11001 ?
b11001 G
b11000 3
b11000 <
b11000 J
b11100 /
b11100 C
b11100 Q
b100000 0
b100000 F
b100000 P
b111 #
1!
#150000
0!
#160000
b100000 /
b100000 C
b100000 Q
b10000000 -
b10000000 L
b10000000 O
b100000 .
b100000 :
b100000 K
b0 6
b0 =
b0 I
b0 9
b0 ?
b0 G
b11100 3
b11100 <
b11100 J
b10 7
b10 >
b10 H
b0 2
b0 ;
b0 M
b1000000010100000 5
b1000000010100000 A
b1000000010100000 N
b100 &
b100 B
b100 S
b1000 #
1!
#170000
0!
#180000
b10011100 5
b10011100 A
b10011100 N
b0 &
b0 B
b0 S
b100000 3
b100000 <
b100000 J
b100100 /
b100100 C
b100100 Q
b1001 #
b100 *
b100 D
b100 U
1!
#190000
0!
#200000
b101000 /
b101000 C
b101000 Q
b100100 3
b100100 <
b100100 J
b10100000 5
b10100000 A
b10100000 N
b0 *
b0 D
b0 U
b1010 #
1!
#210000
0!
#220000
b10100100 5
b10100100 A
b10100100 N
b101000 3
b101000 <
b101000 J
b101100 /
b101100 C
b101100 Q
b1000100010100000100100 0
b1000100010100000100100 F
b1000100010100000100100 P
b1011 #
1!
#230000
0!
#240000
b100000 0
b100000 F
b100000 P
b110000 /
b110000 C
b110000 Q
b100010001010000010010000 -
b100010001010000010010000 L
b100010001010000010010000 O
b10100000100100 .
b10100000100100 :
b10100000100100 K
b11001 6
b11001 =
b11001 I
b11001 9
b11001 ?
b11001 G
b101100 3
b101100 <
b101100 J
b0 7
b0 >
b0 H
b101 2
b101 ;
b101 M
b10101000 5
b10101000 A
b10101000 N
b1100 #
1!
#250000
0!
#260000
b11001 '
b11001 @
b11001 R
b1010000010111100 5
b1010000010111100 A
b1010000010111100 N
b101 &
b101 B
b101 S
b10 7
b10 >
b10 H
b0 2
b0 ;
b0 M
b10000000 -
b10000000 L
b10000000 O
b100000 .
b100000 :
b100000 K
b0 6
b0 =
b0 I
b0 9
b0 ?
b0 G
b110000 3
b110000 <
b110000 J
b110100 /
b110100 C
b110100 Q
b1101 #
1!
#270000
0!
#280000
b111000 /
b111000 C
b111000 Q
b110100 3
b110100 <
b110100 J
b10110000 5
b10110000 A
b10110000 N
b0 &
b0 B
b0 S
b0 '
b0 @
b0 R
b101 *
b101 D
b101 U
b11001 +
b11001 E
b11001 T
b1110 #
1!
#290000
0!
#300000
b10110100 5
b10110100 A
b10110100 N
b111000 3
b111000 <
b111000 J
b111100 /
b111100 C
b111100 Q
b1111 #
b0 *
b0 D
b0 U
b0 +
b0 E
b0 T
1!
#310000
0!
#320000
b1000100011000000100101 0
b1000100011000000100101 F
b1000100011000000100101 P
b1000000 /
b1000000 C
b1000000 Q
b111100 3
b111100 <
b111100 J
b10111000 5
b10111000 A
b10111000 N
b10000 #
1!
#330000
0!
#340000
b10111100 5
b10111100 A
b10111100 N
b1 7
b1 >
b1 H
b110 2
b110 ;
b110 M
b100010001100000010010100 -
b100010001100000010010100 L
b100010001100000010010100 O
b11000000100101 .
b11000000100101 :
b11000000100101 K
b11001 6
b11001 =
b11001 I
b11001 9
b11001 ?
b11001 G
b1000000 3
b1000000 <
b1000000 J
b1000100 /
b1000100 C
b1000100 Q
b100000 0
b100000 F
b100000 P
b10001 #
1!
#350000
0!
#360000
b1001000 /
b1001000 C
b1001000 Q
b10000000 -
b10000000 L
b10000000 O
b100000 .
b100000 :
b100000 K
b0 6
b0 =
b0 I
b0 9
b0 ?
b0 G
b1000100 3
b1000100 <
b1000100 J
b10 7
b10 >
b10 H
b0 2
b0 ;
b0 M
b1100000011010100 5
b1100000011010100 A
b1100000011010100 N
b110 &
b110 B
b110 S
b11001 '
b11001 @
b11001 R
b10010 #
1!
#370000
0!
#380000
b0 '
b0 @
b0 R
b11000100 5
b11000100 A
b11000100 N
b0 &
b0 B
b0 S
b1001000 3
b1001000 <
b1001000 J
b1001100 /
b1001100 C
b1001100 Q
b10011 #
b110 *
b110 D
b110 U
b11001 +
b11001 E
b11001 T
1!
#390000
0!
#400000
b1010000 /
b1010000 C
b1010000 Q
b1001100 3
b1001100 <
b1001100 J
b11001000 5
b11001000 A
b11001000 N
b0 *
b0 D
b0 U
b0 +
b0 E
b0 T
b10100 #
1!
#410000
0!
#420000
b11001100 5
b11001100 A
b11001100 N
b1010000 3
b1010000 <
b1010000 J
b1010100 /
b1010100 C
b1010100 Q
b1000100011100000101010 0
b1000100011100000101010 F
b1000100011100000101010 P
b10101 #
1!
#430000
0!
#440000
b100000 0
b100000 F
b100000 P
b1011000 /
b1011000 C
b1011000 Q
b100010001110000010101000 -
b100010001110000010101000 L
b100010001110000010101000 O
b11100000101010 .
b11100000101010 :
b11100000101010 K
b11001 6
b11001 =
b11001 I
b11001 9
b11001 ?
b11001 G
b1010100 3
b1010100 <
b1010100 J
b111 7
b111 >
b111 H
b111 2
b111 ;
b111 M
b11010000 5
b11010000 A
b11010000 N
b10110 #
1!
#450000
0!
#460000
b1110000011111100 5
b1110000011111100 A
b1110000011111100 N
b111 &
b111 B
b111 S
b10 7
b10 >
b10 H
b0 2
b0 ;
b0 M
b10000000 -
b10000000 L
b10000000 O
b100000 .
b100000 :
b100000 K
b0 6
b0 =
b0 I
b0 9
b0 ?
b0 G
b1011000 3
b1011000 <
b1011000 J
b1011100 /
b1011100 C
b1011100 Q
b10111 #
1!
#470000
0!
#480000
b1100000 /
b1100000 C
b1100000 Q
b1011100 3
b1011100 <
b1011100 J
b11011000 5
b11011000 A
b11011000 N
b0 &
b0 B
b0 S
b111 *
b111 D
b111 U
b11000 #
1!
#490000
0!
#500000
b11011100 5
b11011100 A
b11011100 N
b1100000 3
b1100000 <
b1100000 J
b1100100 /
b1100100 C
b1100100 Q
b11001 #
b0 *
b0 D
b0 U
1!
#510000
0!
#520000
b100000001010000000000000000110 0
b100000001010000000000000000110 F
b100000001010000000000000000110 P
b1101000 /
b1101000 C
b1101000 Q
b1100100 3
b1100100 <
b1100100 J
b11100000 5
b11100000 A
b11100000 N
b11010 #
1!
#530000
0!
#540000
b11100100 5
b11100100 A
b11100100 N
b1000 2
b1000 ;
b1000 M
18
b101000000000000000011000 -
b101000000000000000011000 L
b101000000000000000011000 O
b110 .
b110 :
b110 K
b11001 9
b11001 ?
b11001 G
b1101000 3
b1101000 <
b1101000 J
b1101100 /
b1101100 C
b1101100 Q
b100000 0
b100000 F
b100000 P
b11011 #
1!
#550000
0!
#560000
b1110000 /
b1110000 C
b1110000 Q
b10000000 -
b10000000 L
b10000000 O
b100000 .
b100000 :
b100000 K
b0 9
b0 ?
b0 G
b1101100 3
b1101100 <
b1101100 J
b0 2
b0 ;
b0 M
08
b10000000 5
b10000000 A
b10000000 N
b1000 &
b1000 B
b1000 S
b11111 '
b11111 @
b11111 R
b11100 #
1!
#570000
0!
#580000
b0 '
b0 @
b0 R
b11101100 5
b11101100 A
b11101100 N
b0 &
b0 B
b0 S
b1110000 3
b1110000 <
b1110000 J
b1110100 /
b1110100 C
b1110100 Q
b11101 #
b1000 *
b1000 D
b1000 U
b11111 +
b11111 E
b11111 T
1!
#590000
0!
#600000
b1111000 /
b1111000 C
b1111000 Q
b1110100 3
b1110100 <
b1110100 J
b11110000 5
b11110000 A
b11110000 N
b0 *
b0 D
b0 U
b0 +
b0 E
b0 T
b11110 #
1!
#610000
0!
#620000
b11110100 5
b11110100 A
b11110100 N
b1111000 3
b1111000 <
b1111000 J
b1111100 /
b1111100 C
b1111100 Q
b11111 #
1!
#630000
0!
#640000
b10000000 /
b10000000 C
b10000000 Q
b1111100 3
b1111100 <
b1111100 J
b11111000 5
b11111000 A
b11111000 N
b100000 #
1!
#650000
0!
#660000
b11111100 5
b11111100 A
b11111100 N
b10000000 3
b10000000 <
b10000000 J
b10000100 /
b10000100 C
b10000100 Q
b100001 #
1!
#670000
0!
#680000
b10001000 /
b10001000 C
b10001000 Q
b10000100 3
b10000100 <
b10000100 J
b100000000 5
b100000000 A
b100000000 N
b100010 #
1!
#690000
0!
#700000
b100000100 5
b100000100 A
b100000100 N
b10001000 3
b10001000 <
b10001000 J
b10001100 /
b10001100 C
b10001100 Q
b100011 #
1!
#710000
0!
#720000
bx 0
bx F
bx P
b10010000 /
b10010000 C
b10010000 Q
b10001100 3
b10001100 <
b10001100 J
b100001000 5
b100001000 A
b100001000 N
b100100 #
1!
